odoo/addons/mgmtsystem_quality/README.rst
odoo/addons/mgmtsystem_quality/__init__.py
odoo/addons/mgmtsystem_quality/__manifest__.py
odoo/addons/mgmtsystem_quality/data/mgmtsystem_system.xml
odoo/addons/mgmtsystem_quality/i18n/de.po
odoo/addons/mgmtsystem_quality/i18n/fr.po
odoo/addons/mgmtsystem_quality/i18n/it.po
odoo/addons/mgmtsystem_quality/i18n/mgmtsystem_quality.pot
odoo/addons/mgmtsystem_quality/i18n/nb.po
odoo/addons/mgmtsystem_quality/i18n/pt_BR.po
odoo/addons/mgmtsystem_quality/i18n/sv.po
odoo/addons/mgmtsystem_quality/i18n/vi.po
odoo/addons/mgmtsystem_quality/readme/CONFIGURE.md
odoo/addons/mgmtsystem_quality/readme/CONTRIBUTORS.md
odoo/addons/mgmtsystem_quality/readme/DESCRIPTION.md
odoo/addons/mgmtsystem_quality/readme/ROADMAP.md
odoo/addons/mgmtsystem_quality/readme/USAGE.md
odoo/addons/mgmtsystem_quality/static/description/icon.png
odoo/addons/mgmtsystem_quality/static/description/index.html
odoo_addon_mgmtsystem_quality-18.0.1.0.1.dist-info/METADATA
odoo_addon_mgmtsystem_quality-18.0.1.0.1.dist-info/WHEEL
odoo_addon_mgmtsystem_quality-18.0.1.0.1.dist-info/top_level.txt
odoo_addon_mgmtsystem_quality-18.0.1.0.1.dist-info/RECORD
